{
  "hash": "6bda6536",
  "configHash": "7f7df0a0",
  "lockfileHash": "40bc5069",
  "browserHash": "1a34a927",
  "optimized": {
    "vue": {
      "src": "../../../../../node_modules/vue/dist/vue.runtime.esm-bundler.js",
      "file": "vue.js",
      "fileHash": "51c4a31d",
      "needsInterop": false
    },
    "vitepress > @vue/devtools-api": {
      "src": "../../../../../node_modules/@vue/devtools-api/dist/index.js",
      "file": "vitepress___@vue_devtools-api.js",
      "fileHash": "2f4c4e2b",
      "needsInterop": false
    },
    "vitepress > @vueuse/core": {
      "src": "../../../../../node_modules/vitepress/node_modules/@vueuse/core/index.mjs",
      "file": "vitepress___@vueuse_core.js",
      "fileHash": "bc43d4e9",
      "needsInterop": false
    }
  },
  "chunks": {
    "chunk-FIIBJG54": {
      "file": "chunk-FIIBJG54.js"
    }
  }
}